moysklad_api/__init__.py
moysklad_api/exceptions.py
moysklad_api/loggers.py
moysklad_api/client/__init__.py
moysklad_api/client/api.py
moysklad_api/client/base.py
moysklad_api/client/session/__init__.py
moysklad_api/client/session/base.py
moysklad_api/enums/__init__.py
moysklad_api/enums/bonus_transaction_category_type.py
moysklad_api/enums/bonus_transaction_status.py
moysklad_api/enums/bonus_transaction_type.py
moysklad_api/enums/distribution.py
moysklad_api/enums/entity_type.py
moysklad_api/enums/event_type.py
moysklad_api/enums/group_by.py
moysklad_api/enums/object_type.py
moysklad_api/enums/quantity_mode.py
moysklad_api/enums/source.py
moysklad_api/enums/stock_mode.py
moysklad_api/enums/stock_type.py
moysklad_api/filters/__init__.py
moysklad_api/filters/base.py
moysklad_api/filters/dsl.py
moysklad_api/filters/operators.py
moysklad_api/methods/__init__.py
moysklad_api/methods/base.py
moysklad_api/methods/get_assortment.py
moysklad_api/methods/get_audit.py
moysklad_api/methods/get_bonus_transaction.py
moysklad_api/methods/get_bonus_transactions.py
moysklad_api/methods/get_counterparties.py
moysklad_api/methods/get_counterparty.py
moysklad_api/methods/get_current_stock.py
moysklad_api/methods/get_demand.py
moysklad_api/methods/get_demands.py
moysklad_api/methods/get_events.py
moysklad_api/methods/get_product.py
moysklad_api/methods/get_products.py
moysklad_api/methods/get_profit.py
moysklad_api/methods/get_purchase_order.py
moysklad_api/methods/get_purchase_orders.py
moysklad_api/methods/get_stock.py
moysklad_api/methods/get_token.py
moysklad_api/methods/get_variant.py
moysklad_api/methods/get_variants.py
moysklad_api/methods/get_webhook.py
moysklad_api/methods/get_webhooks.py
moysklad_api/methods/update_product.py
moysklad_api/methods/update_products.py
moysklad_api/methods/update_variant.py
moysklad_api/methods/update_variants.py
moysklad_api/types/__init__.py
moysklad_api/types/account.py
moysklad_api/types/actual_address_full.py
moysklad_api/types/agent.py
moysklad_api-0.5.11a1.dist-info/METADATA
moysklad_api-0.5.11a1.dist-info/WHEEL
moysklad_api-0.5.11a1.dist-info/licenses/LICENSE
moysklad_api-0.5.11a1.dist-info/RECORD
