Metadata-Version: 2.4
Name: moysklad-api
Version: 0.5.11a1
Summary: Мой Склад API
Project-URL: Homepage, https://github.com/serdukow/moysklad-api
Project-URL: Documentation, https://github.com/serdukow/moysklad-api#readme
Project-URL: Repository, https://github.com/serdukow/moysklad-api
Author-email: Andrei Serdiukov <serdukow1@gmail.com>
Maintainer-email: Andrei Serdiukov <serdukow1@gmail.com>
License: MIT
License-File: LICENSE
Keywords: api,async,client,moysklad,мой склад
Classifier: Development Status :: 2 - Pre-Alpha
Classifier: Intended Audience :: Developers
Classifier: License :: OSI Approved :: MIT License
Classifier: Programming Language :: Python :: 3
Classifier: Programming Language :: Python :: 3.13
Classifier: Topic :: Software Development :: Libraries :: Python Modules
Requires-Python: <3.14,>=3.10
Requires-Dist: aiolimiter<2.0.0,>=1.2.1
Requires-Dist: httpx<0.29.0,>=0.28.1
Requires-Dist: pydantic<2.12.2,>=2.4.1
Provides-Extra: dev
Requires-Dist: pre-commit<5.0.0,>=4.3.0; extra == 'dev'
Requires-Dist: ruff<0.15.0,>=0.14.1; extra == 'dev'
Provides-Extra: lint
Requires-Dist: pre-commit<5.0.0,>=4.3.0; extra == 'lint'
Requires-Dist: ruff<0.15.0,>=0.14.1; extra == 'lint'
Provides-Extra: test
Requires-Dist: pytest-asyncio<2.0.0,>=1.2.0; extra == 'test'
Requires-Dist: pytest<9.0.0,>=8.4.2; extra == 'test'
Requires-Dist: python-dotenv<2.0.0,>=1.2.1; extra == 'test'
